plot_shift-0.2.5.dist-info/METADATA
plot_shift-0.2.5.dist-info/WHEEL
plot_shift-0.2.5.dist-info/entry_points.txt
plot_shift-0.2.5.dist-info/licenses/LICENSE
plot_shift/__init__.py
plot_shift/correlation_plot.py
plot_shift/profit_based_thresholds_plot.py
plot_shift/silhouette_diagram.py
plot_shift-0.2.5.dist-info/RECORD
