Metadata-Version: 2.1
Name: plot-shift
Version: 0.2.5
Summary: A Python package for advanced plotting utilities.
Author-Email: Koen van Esterik <koen@vanesterik.com>
License: MIT
Classifier: Programming Language :: Python :: 3
Classifier: Programming Language :: Python :: 3.8
Classifier: Programming Language :: Python :: 3.9
Classifier: Programming Language :: Python :: 3.10
Classifier: Programming Language :: Python :: 3.11
Classifier: License :: OSI Approved :: MIT License
Classifier: Operating System :: OS Independent
Project-URL: Homepage, https://pypi.org/project/plot-shift/
Project-URL: Repository, https://github.com/koendirkvanesterik/plot-shift
Requires-Python: <4.0,>=3.8
Requires-Dist: matplotlib>=3.10.3
Requires-Dist: numpy>=2.2.6
